Metadata-Version: 1.0
Name: pgwrap
Version: 0.6
Summary: Simple PostgreSQL database wrapper - provides wrapper over psycopg2 supporting a Python API for common sql functions
Home-page: https://github.com/paulchakravarti/pgwrap
Author: Paul Chakravarti
Author-email: paul.chakravarti@gmail.com
License: BSD
Platform: UNKNOWN
Classifier: Topic :: Database
